{
  "getPNRHistory": {
    "flightsHistory": "     *****      AIR HISTORY                 KHCR5P    *****\nXS SU1521 N 02JUN NUXSVO NN/HK1  1350  1530  O*      1\nXS SU1274 N 02JUN SVOKRR NN/HK1  2150   005  O*      1\nRCVD-TWIKETGWS/Z75ZMGWS\nCRDT- MOW/75ZM/1G AG WS       1853Z/01JUN\nHS SU1521 N 02JUN NUXSVO NN/HS1  1350  1530  O       1\nHS SU1274 N 02JUN SVOKRR NN/HS1  2150   005  O       1\nRCVD-LEONIDRYABOSHTAN/Z75ZMGWS\nCRDT- MOW/75ZM/1G AG WS       1823Z/01JUN",
    "vendorRemarks": "     *****  NO  VENDOR REMARKS HISTORY      KHCR5P    *****",
    "ssrs": "     *****      SERVICE INFORMATION HISTORY KHCR5P    *****\n** SEGMENT/PASSENGER RELATED **\nHSI SU 1521 N  02 JUN NUXSVO\nXG   1.DEMIANOV/EVGENI# NN/HK001  TKNE  5553786210951C1\nHSI SU 1274 N  02 JUN SVOKRR\nXG   1.DEMIANOV/EVGENI# NN/HK001  TKNE  5553786210951C2\nRCVD-TWIKETGWS/Z75ZMGWS\nCRDT- MOW/75ZM/1G AG WS       1853Z/01JUN\n** CARRIER RELATED **\nAO    SU ANNULIROWANO PO ZAPROSU ZAKAZCHIKA\nRCVD-TWIKETGWS/ZGWS\nCRDT- MOW/75ZM/1G AG IF       1853Z/01JUN\n** SEGMENT/PASSENGER RELATED **\nHSI SU 1521 N  02 JUN NUXSVO\nAG   1.DEMIANOV/EVGENI# NN/PN001  TKNE  5553786210951C1\nHSI SU 1274 N  02 JUN SVOKRR\nAG   1.DEMIANOV/EVGENI# NN/PN001  TKNE  5553786210951C2\nRCVD-\nCRDT- MOW/75ZM/1G AG          1825Z/01JUN\n** CARRIER RELATED **\nAO    SU PAX CONTACT 79370007700\nAO    SU CTCP79370007700 M\nAO    SU CTCM NUX 79370007700 DEMIANOV/EVGENIIVALEREVICH/P1\nAO    SU CTCE 5E4295B0128758B7D45F236A//CLIENTS.ONETWOTRIP.COM\nAO    SSRCTCMSU HK001 /79370007700\nAO    SSRCTCESU HK001 /5E4295B0128758B7D45F236A//CLIENTS.ONETWOT)><\nAO    SSRCTCESU HK001 /5E4295B0128758B7D45F236A//CLIENTS.ONETWOT    RIP.COM\nRCVD-TWIKETGWS/ZGWS\nCRDT- MOW/75ZM/1G AG IF       1825Z/01JUN\nAO    SSRDOCSSU HK001 /P/RU/XXXXXX7985/RU/XXXXXXX/M/01JUN25/DEMI    ANOV/EVGENIIVALEREVICH\nRCVD-TWIKETGWS/ZGWS\nCRDT- MOW/75ZM/1G AG IF       1825Z/01JUN",
    "fullHistory": "     *****      HISTORY                     KHCR5P    *****\n** ONLY ACTIVE PRODUCTS EXIST **\n** ORIGINAL CREATOR **\nRCVD-LEONIDRYABOSHTAN/75ZMGWS\nCRDT- MOW         AG WS       1823Z/01JUN\n** HISTORY **\nXQ QR/13 QSBSB BDDA8C \nCRDT- QSB/75ZM/1G AG 50       2056Z/02JUN\nAQ 02JUN 2056 PROG. QUEUED TO Q13 75ZM BY PCE6\nXQ QR/13 QSBSB BDDA8C \nCRDT- QSB/75ZM/1G AG 50       2041Z/02JUN\nAQ 02JUN 2041 PROG. QUEUED TO Q13 75ZM BY PCE6\nXQ QR/13 QSBSB BDDA8C \nCRDT- QSB/75ZM/1G AG 50       2026Z/02JUN\nAQ 02JUN 2026 PROG. QUEUED TO Q13 75ZM BY PCE6\nXQ QR/13 QSBSB BDDA8C \nCRDT- QSB/75ZM/1G AG 50       2011Z/02JUN\nAQ 02JUN 2011 PROG. QUEUED TO Q13 75ZM BY PCE6\nXQ QR/13 QSBSB BDDA8C \nCRDT- QSB/75ZM/1G AG 50       1956Z/02JUN\nAQ 02JUN 1956 PROG. QUEUED TO Q13 75ZM BY PCE6\nXQ QR/13 QSBSB BDDA8C \nCRDT- QSB/75ZM/1G AG 50       1941Z/02JUN\nAQ 02JUN 1941 PROG. QUEUED TO Q13 75ZM BY PCE6\nXQ QR/13 QSBSB BDDA8C \nCRDT- QSB/75ZM/1G AG 50       1926Z/02JUN\nAQ 02JUN 1926 PROG. QUEUED TO Q13 75ZM BY PCE6\nXQ QR/13 QSBSB BDDA8C \nCRDT- QSB/75ZM/1G AG 50       1911Z/02JUN\nAQ 02JUN 1911 PROG. QUEUED TO Q13 75ZM BY PCE6\nXQ QR/13 QSBSB BDDA8C \nCRDT- QSB/75ZM/1G AG 50       1856Z/02JUN\nAQ 02JUN 1856 PROG. QUEUED TO Q13 75ZM BY PCE6\nXQ QR/13 QSBSB BDDA8C \nCRDT- QSB/75ZM/1G AG 50       1841Z/02JUN\nAQ 02JUN 1841 PROG. QUEUED TO Q13 75ZM BY PCE6\nXQ QR/13 QSBSB BDDA8C \nCRDT- QSB/75ZM/1G AG 50       1826Z/02JUN\nAQ 02JUN 1826 PROG. QUEUED TO Q13 75ZM BY PCE6\nXQ QR/13 QSBSB BDDA8C \nCRDT- QSB/75ZM/1G AG 50       1811Z/02JUN\nAQ 02JUN 1811 PROG. QUEUED TO Q13 75ZM BY PCE6\nXQ QR/13 QSBSB BDDA8C \nCRDT- QSB/75ZM/1G AG 50       1756Z/02JUN\nAQ 02JUN 1756 PROG. QUEUED TO Q13 75ZM BY PCE6\nXQ QR/13 QSBSB BDDA8C \nCRDT- QSB/75ZM/1G AG 50       1741Z/02JUN\nAQ 02JUN 1741 PROG. QUEUED TO Q13 75ZM BY PCE6\nXQ QR/13 QSBSB BDDA8C \nCRDT- QSB/75ZM/1G AG 50       1726Z/02JUN\nAQ 02JUN 1726 PROG. QUEUED TO Q13 75ZM BY PCE6\nXQ QR/13 QSBSB BDDA8C \nCRDT- QSB/75ZM/1G AG 50       1711Z/02JUN\nAQ 02JUN 1711 PROG. QUEUED TO Q13 75ZM BY PCE6\nXQ QR/13 QSBSB BDDA8C \nCRDT- QSB/75ZM/1G AG 50       1656Z/02JUN\nAQ 02JUN 1656 PROG. QUEUED TO Q13 75ZM BY PCE6\nXQ QR/13 QSBSB BDDA8C \nCRDT- QSB/75ZM/1G AG 50       1641Z/02JUN\nAQ 02JUN 1641 PROG. QUEUED TO Q13 75ZM BY PCE6\nXQ QR/13 QSBSB BDDA8C \nCRDT- QSB/75ZM/1G AG 50       1626Z/02JUN\nAQ 02JUN 1626 PROG. QUEUED TO Q13 75ZM BY PCE6\nXQ QR/13 QSBSB BDDA8C \nCRDT- QSB/75ZM/1G AG 50       1611Z/02JUN\nAQ 02JUN 1611 PROG. QUEUED TO Q13 75ZM BY PCE6\nXQ QR/13 QSBSB BDDA8C \nCRDT- QSB/75ZM/1G AG 50       1556Z/02JUN\nAQ 02JUN 1556 PROG. QUEUED TO Q13 75ZM BY PCE6\nXQ QR/13 QSBSB BDDA8C \nCRDT- QSB/75ZM/1G AG 50       1541Z/02JUN\nAQ 02JUN 1541 PROG. QUEUED TO Q13 75ZM BY PCE6\nXQ QR/13 QSBSB BDDA8C \nCRDT- QSB/75ZM/1G AG 50       1526Z/02JUN\nAQ 02JUN 1526 PROG. QUEUED TO Q13 75ZM BY PCE6\nXQ QR/13 QSBSB BDDA8C \nCRDT- QSB/75ZM/1G AG 50       1511Z/02JUN\nAQ 02JUN 1511 PROG. QUEUED TO Q13 75ZM BY PCE6\nXQ QR/13 QSBSB BDDA8C \nCRDT- QSB/75ZM/1G AG 50       1456Z/02JUN\nAQ 02JUN 1456 PROG. QUEUED TO Q13 75ZM BY PCE6\nXQ QR/13 QSBSB BDDA8C \nCRDT- QSB/75ZM/1G AG 50       1441Z/02JUN\nAQ 02JUN 1441 PROG. QUEUED TO Q13 75ZM BY PCE6\nXQ QR/13 QSBSB BDDA8C \nCRDT- QSB/75ZM/1G AG 50       1426Z/02JUN\nAQ 02JUN 1426 PROG. QUEUED TO Q13 75ZM BY PCE6\nXQ QR/13 QSBSB BDDA8C \nCRDT- QSB/75ZM/1G AG 50       1411Z/02JUN\nAQ 02JUN 1411 PROG. QUEUED TO Q13 75ZM BY PCE6\nXQ QR/13 QSBSB BDDA8C \nCRDT- QSB/75ZM/1G AG 50       1356Z/02JUN\nAQ 02JUN 1356 PROG. QUEUED TO Q13 75ZM BY PCE6\nXQ QR/13 QSBSB BDDA8C \nCRDT- QSB/75ZM/1G AG 50       1341Z/02JUN\nAQ 02JUN 1341 PROG. QUEUED TO Q13 75ZM BY PCE6\nXQ QR/13 QSBSB BDDA8C \nCRDT- QSB/75ZM/1G AG 50       1326Z/02JUN\nAQ 02JUN 1326 PROG. QUEUED TO Q13 75ZM BY PCE6\nXQ QR/13 QSBSB BDDA8C \nCRDT- QSB/75ZM/1G AG 50       1311Z/02JUN\nAQ 02JUN 1311 PROG. QUEUED TO Q13 75ZM BY PCE6\nXQ QR/13 QSBSB BDDA8C \nCRDT- QSB/75ZM/1G AG 50       1256Z/02JUN\nAQ 02JUN 1256 PROG. QUEUED TO Q13 75ZM BY PCE6\nXQ QR/13 QSBSB BDDA8C \nCRDT- QSB/75ZM/1G AG 50       1241Z/02JUN\nAQ 02JUN 1241 PROG. QUEUED TO Q13 75ZM BY PCE6\nXQ QR/13 QSBSB BDDA8C \nCRDT- QSB/75ZM/1G AG 50       1226Z/02JUN\nAQ 02JUN 1226 PROG. QUEUED TO Q13 75ZM BY PCE6\nXQ QR/13 QSBSB BDDA8C \nCRDT- QSB/75ZM/1G AG 50       1211Z/02JUN\nAQ 02JUN 1211 PROG. QUEUED TO Q13 75ZM BY PCE6\nXQ QR/13 QSBSB BDDA8C \nCRDT- QSB/75ZM/1G AG 50       1156Z/02JUN\nAQ 02JUN 1156 PROG. QUEUED TO Q13 75ZM BY PCE6\nXQ QR/13 QSBSB BDDA8C \nCRDT- QSB/75ZM/1G AG 50       1141Z/02JUN\nAQ 02JUN 1141 PROG. QUEUED TO Q13 75ZM BY PCE6\nXQ QR/13 QSBSB BDDA8C \nCRDT- QSB/75ZM/1G AG 50       1126Z/02JUN\nAQ 02JUN 1126 PROG. QUEUED TO Q13 75ZM BY PCE6\nXQ QR/13 QSBSB BDDA8C \nCRDT- QSB/75ZM/1G AG 50       1111Z/02JUN\nAQ 02JUN 1111 PROG. QUEUED TO Q13 75ZM BY PCE6\nXQ QR/13 QSBSB BDDA8C \nCRDT- QSB/75ZM/1G AG 50       1056Z/02JUN\nAQ 02JUN 1056 PROG. QUEUED TO Q13 75ZM BY PCE6\nXQ QR/13 QSBSB BDDA8C \nCRDT- QSB/75ZM/1G AG 50       1035Z/02JUN\nAQ 02JUN 1035 PROG. QUEUED TO Q13 75ZM BY PCE6\nAQ 02JUN 1021 PROG. QUEUED TO Q13 75ZM BY PCE6\nXQ QR/13 QSBSB BDDA8C \nCRDT- QSB/75ZM/1G AG 50       1004Z/02JUN\nAQ 02JUN 1004 PROG. QUEUED TO Q13 75ZM BY PCE6\nXQ QR/13 QSBSB BDDA8C \nCRDT- QSB/75ZM/1G AG 50       0949Z/02JUN\nAQ 02JUN 0949 PROG. QUEUED TO Q13 75ZM BY PCE6\nXQ QR/13 QSBSB BDDA8C \nCRDT- QSB/75ZM/1G AG 50       0934Z/02JUN\nAQ 02JUN 0934 PROG. QUEUED TO Q13 75ZM BY PCE6\nXQ QR/13 QSBSB BDDA8C \nCRDT- QSB/75ZM/1G AG 50       0919Z/02JUN\nAQ 02JUN 0919 PROG. QUEUED TO Q13 75ZM BY PCE6\nXQ QR/13 QSBSB BDDA8C \nCRDT- QSB/75ZM/1G AG 50       0904Z/02JUN\nAQ 02JUN 0904 PROG. QUEUED TO Q13 75ZM BY PCE6\nXQ QR/13 QSBSB BDDA8C \nCRDT- QSB/75ZM/1G AG 50       0849Z/02JUN\nAQ 02JUN 0849 PROG. QUEUED TO Q13 75ZM BY PCE6\nXQ QR/13 QSBSB BDDA8C \nCRDT- QSB/75ZM/1G AG 50       0834Z/02JUN\nAQ 02JUN 0834 PROG. QUEUED TO Q13 75ZM BY PCE6\nXQ QR/13 QSBSB BDDA8C \nCRDT- QSB/75ZM/1G AG 50       0819Z/02JUN\nAQ 02JUN 0819 PROG. QUEUED TO Q13 75ZM BY PCE6\nXQ QR/13 QSBSB BDDA8C \nCRDT- QSB/75ZM/1G AG 50       0804Z/02JUN\nAQ 02JUN 0804 PROG. QUEUED TO Q13 75ZM BY PCE6\nXQ QR/13 QSBSB BDDA8C \nCRDT- QSB/75ZM/1G AG 50       0749Z/02JUN\nAQ 02JUN 0749 PROG. QUEUED TO Q13 75ZM BY PCE6\nXQ QR/13 QSBSB BDDA8C \nCRDT- QSB/75ZM/1G AG 50       0734Z/02JUN\nAQ 02JUN 0734 PROG. QUEUED TO Q13 75ZM BY PCE6\nXS SU1521 N 02JUN NUXSVO NN/HK1  1350  1530  O*      1\nXS SU1274 N 02JUN SVOKRR NN/HK1  2150   005  O*      1\nXFQ DEMIANOV/EVGENIIVALERE-ADT  T  RUB    17310      01JUN20\nAOB DEMIANOV/EVGENIIVALERE-ADT  TTLRUB    17310      01JUN20\nAOB DEMIANOV/EVGENIIVALERE-ADT     RUB        0     01JUN20\n>XFQP1/-*75ZM\n      NUX SU X/MOW SU KRR 13300 RUB13300END\n    S1   FB-NCOR\n         BG-1PC  NB-02JUN    NA-02JUN X\n    S2   FB-NCOR\n         BG-1PC  NB-02JUN    NA-02JUN\n    T P01/S1-2/ZA1.00/ET/EBINCL VAT 1481.82RUB YR*EB49.09RUB/CSU* SERVICE INFORMATION HISTORY EXISTS >*HSI;\nRCVD-TWIKETGWS/Z75ZMGWS\nCRDT- MOW/75ZM/1G AG WS       1853Z/01JUN\n* SERVICE INFORMATION HISTORY EXISTS >*HSI;\nRCVD-TWIKETGWS/ZGWS\nCRDT- MOW/75ZM/1G AG IF       1853Z/01JUN\nXFQ DEMIANOV/EVGENIIVALERE-ADT  G  RUB    17310      01JUN20\nAOB DEMIANOV/EVGENIIVALERE-ADT  TTLRUB    17310      01JUN20\nAOB DEMIANOV/EVGENIIVALERE-ADT     RUB        0     01JUN20\nAFQ DEMIANOV/EVGENIIVALERE-ADT  G              5553786210951\nXFQ DEMIANOV/EVGENIIVALERE-ADT  G  RUB    17310      01JUN20\nAOB DEMIANOV/EVGENIIVALERE-ADT  TTLRUB    17310      01JUN20\nAOB DEMIANOV/EVGENIIVALERE-ADT     RUB        0     01JUN20\nAFQ DEMIANOV/EVGENIIVALERE-ADT  G              5553786210951\n* SERVICE INFORMATION HISTORY EXISTS >*HSI;\nRCVD-\nCRDT- MOW/75ZM/1G AG          1825Z/01JUN\nXT TAU/01JUN/2343/X\nAT P01/S01.02/ZA1.00/EBINCL VAT 1481.82RUB YR*EB49.09RUB/FS/CSU\nRCVD-/Z75ZMGWS\nCRDT- MOW/75ZM/1G AG WS       1825Z/01JUN\n* SERVICE INFORMATION HISTORY EXISTS >*HSI;\nRCVD-TWIKETGWS/ZGWS\nCRDT- MOW/75ZM/1G AG IF       1825Z/01JUN\nAMT 5e4295b0128758b7d45f236a@XXXXXXX.XXXXXXXXXX.XXX\n* SERVICE INFORMATION HISTORY EXISTS >*HSI;\nRCVD-TWIKETGWS/ZGWS\nCRDT- MOW/75ZM/1G AG IF       1825Z/01JUN\nAQ 01JUN 1823 PROG. QUEUED TO Q10 75ZM BY PCF6\nXT TAU/02JUN\nAT TAU/01JUN/2343/X\nRCVD-TWIKETGWS/ZGWS\nCRDT- MOW/75ZM/1G AG IF       1823Z/01JUN\nAS T   **   TEXT  **    02DEC**E-TICKET**\nRCVD-SU/Z75ZMGWS\nCRDT- MOW/75ZM/1G AG WS       1823Z/01JUN\nVLR SU1521 N 02JUN NUXSVO NN/HK1  1350  1530  O*      1\nVLR SU1274 N 02JUN SVOKRR NN/HK1  2150   005  O*      1\nAVL SU*TYMZLS HDQRMSU 01JUN 1823\nRCVD-\nCRDT- /    /1G         1823Z/01JUN\nAQ 01JUN 1823 PROG. QUEUED TO Q10 75ZM BY PCF6\nHS SU1521 N 02JUN NUXSVO NN/HS1  1350  1530  O       1\nHS SU1274 N 02JUN SVOKRR NN/HS1  2150   005  O       1\nAT TAU/02JUN\nRCVD-LEONIDRYABOSHTAN/Z75ZMGWS"
  },
  "profile": {
    "name": "typicode"
  }
}
